__init__.py
digikuery.py
digikuery-20230529.post2.dist-info/METADATA
digikuery-20230529.post2.dist-info/WHEEL
digikuery-20230529.post2.dist-info/entry_points.txt
digikuery-20230529.post2.dist-info/top_level.txt
digikuery-20230529.post2.dist-info/RECORD
