Metadata-Version: 2.1
Name: digikuery
Version: 20230529.post2
Summary: Digikam database query tool
Author-email: Laurent Ghigonis <ooookiwi@gmail.com>
License: BSD-3-Clause
Project-URL: Homepage, https://github.com/looran/digikuery
Keywords: digikam,database,query
Requires-Python: >=3.0
Requires-Dist: sqlalchemy
